__init__.py
utils.py
whoislite-0.0.1.dist-info/licenses/LICENSE
whoislite-0.0.1.dist-info/METADATA
whoislite-0.0.1.dist-info/WHEEL
whoislite-0.0.1.dist-info/top_level.txt
whoislite-0.0.1.dist-info/RECORD
