Metadata-Version: 2.4
Name: whoislite
Version: 0.0.1
Summary: WhoisLite is a fast, pure Python library for querying WHOIS information for domain names across hundreds of TLDs.
Author-email: Kalinin Mitko <kalinin.mitko@gmail.com>
License: MIT License
Project-URL: Homepage, https://github.com/null-none/whoislite
Keywords: python,whois,whois-loopup,whois-query,whois-client
Classifier: License :: OSI Approved :: MIT License
Classifier: Programming Language :: Python
Classifier: Programming Language :: Python :: 3
Requires-Python: >=3.9
License-File: LICENSE
Provides-Extra: dev
Requires-Dist: pip-tools; extra == "dev"
Dynamic: license-file
